wxflows/__init__.py
wxflows/rag.py
wxflows-0.0.1.dist-info/LICENSE
wxflows-0.0.1.dist-info/METADATA
wxflows-0.0.1.dist-info/WHEEL
wxflows-0.0.1.dist-info/top_level.txt
wxflows-0.0.1.dist-info/RECORD
