Metadata-Version: 2.1
Name: wxflows
Version: 0.0.1
Summary: The wxflows SDK
Author-email: Samuel Hill <sam.hill@ibm.com>
Classifier: Programming Language :: Python :: 3
Classifier: License :: OSI Approved :: MIT License
Classifier: Operating System :: OS Independent
Requires-Python: >=3.8
License-File: LICENSE
